undecorate.py
undecorate-0.2.1.dist-info/DESCRIPTION.rst
undecorate-0.2.1.dist-info/METADATA
undecorate-0.2.1.dist-info/metadata.json
undecorate-0.2.1.dist-info/RECORD
undecorate-0.2.1.dist-info/top_level.txt
undecorate-0.2.1.dist-info/WHEEL
