Metadata-Version: 2.0
Name: undecorate
Version: 0.2.1
Summary: Let your decorations be undone
Home-page: https://github.com/ryanhiebert/undecorate
Author: Ryan Hiebert
Author-email: ryan@ryanhiebert.com
License: MIT
Platform: UNKNOWN
Classifier: Development Status :: 3 - Alpha
Classifier: Programming Language :: Python :: 2
Classifier: Programming Language :: Python :: 2.6
Classifier: Programming Language :: Python :: 2.7
Classifier: Programming Language :: Python :: 3
Classifier: Programming Language :: Python :: 3.2
Classifier: Programming Language :: Python :: 3.3
Classifier: Programming Language :: Python :: 3.4
Classifier: Programming Language :: Python :: Implementation :: PyPy
Classifier: Programming Language :: Python :: Implementation :: CPython
Classifier: Intended Audience :: Developers
